Workbook

Sheet US Payroll Analysis DashBoard
A4: Department | B4: Total Payroll
A5: D21 - Department of Housing | B5: =SUMIF('US Employee Payroll Cleaned'!D:D,A5,'US Employee Payroll Cleaned'!A:A) -> 389719.67
A6: D27 - Department of Finance | B6: =SUMIF('US Employee Payroll Cleaned'!D:D,A6,'US Employee Payroll Cleaned'!A:A) -> 7571.5
A7: D38 - Department of Fleet and Facility Management | B7: =SUMIF('US Employee Payroll Cleaned'!D:D,A7,'US Employee Payroll Cleaned'!A:A) -> 3316.59
A8: D50 - Department of Family and Support Services | B8: =SUMIF('US Employee Payroll Cleaned'!D:D,A8,'US Employee Payroll Cleaned'!A:A) -> 180.08
A9: D54 - Department of Planning and Development | B9: =SUMIF('US Employee Payroll Cleaned'!D:D,A9,'US Employee Payroll Cleaned'!A:A) -> 1187060.2
A10: D57 - Chicago Police Department | B10: =SUMIF('US Employee Payroll Cleaned'!D:D,A10,'US Employee Payroll Cleaned'!A:A) -> 101874.78
A11: D59 - Chicago Fire Department | B11: =SUMIF('US Employee Payroll Cleaned'!D:D,A11,'US Employee Payroll Cleaned'!A:A) -> 20075.58
A12: D58 - Office of Emergency Management and Communications | B12: =SUMIF('US Employee Payroll Cleaned'!D:D,A12,'US Employee Payroll Cleaned'!A:A) -> 5416.08
A13: D67 - Department of Buildings | B13: =SUMIF('US Employee Payroll Cleaned'!D:D,A13,'US Employee Payroll Cleaned'!A:A) -> 769.44
A14: D73 - Chicago Animal Care and Control | B14: =SUMIF('US Employee Payroll Cleaned'!D:D,A14,'US Employee Payroll Cleaned'!A:A) -> 1934
A15: D81 - Department of Streets and Sanitation | B15: =SUMIF('US Employee Payroll Cleaned'!D:D,A15,'US Employee Payroll Cleaned'!A:A) -> 6530.21
A16: D84 - Chicago Department of Transportation | B16: =SUMIF('US Employee Payroll Cleaned'!D:D,A16,'US Employee Payroll Cleaned'!A:A) -> 10964.9
... A19: D88 - Department of Water Management | B19: =SUMIF('US Employee Payroll Cleaned'!D:D,A19,'US Employee Payroll Cleaned'!A:A) -> 6034.94
A20: US EMPLOYEE PAYROLL ANALYSIS DASHHBOARD
A21: Total Payroll | B21: =SUM('US Employee Payroll Cleaned'!A:A) -> 1744230
A22: Average Payroll | B22: =AVERAGE('US Employee Payroll Cleaned'!A:A) -> 3495.4509
A23: Number of records | B23: =COUNTA('US Employee Payroll Cleaned'!G:G) -> 500

Sheet US Employee Payroll Analytics
A1: AMOUNT | B1: FUND TYPE | C1: FUND | D1: DEPARTMENT FUNCTION | E1: DEPARTMENT | F1: APPROPRIATION | G1: TITLE | H1: EMPLOYEE DATASET ID | I1: EMPLOYEE | J1: PAY ELEMENT | K1: PAYROLL YEAR | L1: PAYROLL PERIOD | M1: DEPARTMENT CODE | N1: FUND CODE | O1: APPROPRIATION CODE | P1: TITLE CODE | Q1: RECORD ID
A2: $3,556 | B2: CORPORATE FUND | C2: F0100 - CORPORATE FUND | D2: City Development | E2: D54 - Department of Planning and Development | F2: A0005 - SALARIES AND WAGES - ON PAYROLL | G2: T0109 - ACCOUNTING TECHNICIAN | H2: C1081EDB5EEAE1 | I2: C1081EDB5EEAE1 - TACCAD, CLARIBEL | J2: REGULAR SALARY | K2: 2023 | L2: 1 | M2: D54 | N2: F0100 | O2: A0005 | P2: T0109 | Q2: C1081EDB5EEAE12023142455196394809
A3: $3,902.5 | B3: CORPORATE FUND | C3: F0100 - CORPORATE FUND | D3: City Development | E3: D54 - Department of Planning and Development | F3: A0005 - SALARIES AND WAGES - ON PAYROLL | G3: T0303 - ADMINISTRATIVE ASST III | H3: 90D4F9839B1EE3 | I3: 90D4F9839B1EE3 - GRAYER, SHELIA D | J3: REGULAR SALARY | K3: 2023 | L3: 1 | M3: D54 | N3: F0100 | O3: A0005 | P3: T0303 | Q3: 90D4F9839B1EE320231500216338519161
A4: $3,160.5 | B4: CORPORATE FUND | C4: F0100 - CORPORATE FUND | D4: City Development | E4: D54 - Department of Planning and Development | F4: A0005 - SALARIES AND WAGES - ON PAYROLL | G4: T1405 - CITY PLANNER V | H4: 4146A18BC5805C | I4: 4146A18BC5805C - CORPUZ, BENJAMIN A | J4: REGULAR SALARY | K4: 2023 | L4: 1 | M4: D54 | N4: F0100 | O4: A0005 | P4: T1405 | Q4: 4146A18BC5805C20231371115816750534
A5: $3,711.5 | B5: CORPORATE FUND | C5: F0100 - CORPORATE FUND | D5: City Development | E5: D54 - Department of Planning and Development | F5: A0005 - SALARIES AND WAGES - ON PAYROLL | G5: T1405 - CITY PLANNER V | H5: 73BA524443E82D | I5: 73BA524443E82D - THRUN, EMILY | J5: REGULAR SALARY | K5: 2023 | L5: 1 | M5: D54 | N5: F0100 | O5: A0005 | P5: T1405 | Q5: 73BA524443E82D20231918844264279950
A6: $3,340.5 | B6: CORPORATE FUND | C6: F0100 - CORPORATE FUND | D6: City Development | E6: D54 - Department of Planning and Development | F6: A0005 - SALARIES AND WAGES - ON PAYROLL | G6: T5402 - ARCHITECT II | H6: FABEBFAD17362B | I6: FABEBFAD17362B - BARTON, EMILY M | J6: REGULAR SALARY | K6: 2023 | L6: 1 | M6: D54 | N6: F0100 | O6: A0005 | P6: T5402 | Q6: FABEBFAD17362B20231891354375792176
A7: $4,274 | B7: CORPORATE FUND | C7: F0100 - CORPORATE FUND | D7: City Development | E7: D54 - Department of Planning and Development | F7: A0005 - SALARIES AND WAGES - ON PAYROLL | G7: T5432 - CHIEF LANDSCAPE PLAN EXAMINER | H7: 9B82270E9FBFC9 | I7: 9B82270E9FBFC9 - DAYE, RONALD J | J7: REGULAR SALARY | K7: 2023 | L7: 1 | M7: D54 | N7: F0100 | O7: A0005 | P7: T5432 | Q7: 9B82270E9FBFC920231680319481831943
A8: $-194.51 | B8: CORPORATE FUND | C8: F0100 - CORPORATE FUND | D8: City Development | E8: D54 - Department of Planning and Development | F8: A0005 - SALARIES AND WAGES - ON PAYROLL | G8: T0313 - ASST COMMISSIONER | H8: 0A30E99A8A025B | I8: 0A30E99A8A025B - ALBERT, DAMIAN K | J8: DOCK | K8: 2023 | L8: 2 | M8: D54 | N8: F0100 | O8: A0005 | P8: T0313 | Q8: 0A30E99A8A025B20232415253293962003
A9: $5,212 | B9: CORPORATE FUND | C9: F0100 - CORPORATE FUND | D9: City Development | E9: D54 - Department of Planning and Development | F9: A0005 - SALARIES AND WAGES - ON PAYROLL | G9: T0118 - DIRECTOR OF FINANCE | H9: B8E59990646B62 | I9: B8E59990646B62 - BUDNIK, ALESSANDRA C | J9: REGULAR SALARY | K9: 2023 | L9: 2 | M9: D54 | N9: F0100 | O9: A0005 | P9: T0118 | Q9: B8E59990646B622023279498489467265
A10: $3,902.5 | B10: CORPORATE FUND | C10: F0100 - CORPORATE FUND | D10: City Development | E10: D54 - Department of Planning and Development | F10: A0005 - SALARIES AND WAGES - ON PAYROLL | G10: T0303 - ADMINISTRATIVE ASST III | H10: 90D4F9839B1EE3 | I10: 90D4F9839B1EE3 - GRAYER, SHELIA D | J10: REGULAR SALARY | K10: 2023 | L10: 2 | M10: D54 | N10: F0100 | O10: A0005 | P10: T0303 | Q10: 90D4F9839B1EE320232197657932526116
A11: $2,542.5 | B11: CORPORATE FUND | C11: F0100 - CORPORATE FUND | D11: City Development | E11: D54 - Department of Planning and Development | F11: A0005 - SALARIES AND WAGES - ON PAYROLL | G11: T1293 - SENIOR ZONING PLAN EXAMINER | H11: D6F0FB9FC44E17 | I11: D6F0FB9FC44E17 - NOLTER, ROBERT J | J11: REGULAR SALARY | K11: 2023 | L11: 2 | M11: D54 | N11: F0100 | O11: A0005 | P11: T1293 | Q11: D6F0FB9FC44E1720232226438981182826
A12: $3,240.5 | B12: CORPORATE FUND | C12: F0100 - CORPORATE FUND | D12: City Development | E12: D54 - Department of Planning and Development | F12: A0005 - SALARIES AND WAGES - ON PAYROLL | G12: T1293 - SENIOR ZONING PLAN EXAMINER | H12: 92E1F59DF1DF8D | I12: 92E1F59DF1DF8D - BERAN, PETER D | J12: REGULAR SALARY | K12: 2023 | L12: 2 | M12: D54 | N12: F0100 | O12: A0005 | P12: T1293 | Q12: 92E1F59DF1DF8D20232725595860732288
A13: $3,711.5 | B13: CORPORATE FUND | C13: F0100 - CORPORATE FUND | D13: City Development | E13: D54 - Department of Planning and Development | F13: A0005 - SALARIES AND WAGES - ON PAYROLL | G13: T1405 - CITY PLANNER V | H13: 73BA524443E82D | I13: 73BA524443E82D - THRUN, EMILY | J13: REGULAR SALARY | K13: 2023 | L13: 2 | M13: D54 | N13: F0100 | O13: A0005 | P13: T1405 | Q13: 73BA524443E82D20232743816382565908
... A327: $4,982.5 | B327: CORPORATE FUND | C327: F0100 - CORPORATE FUND | D327: Finance and Administration | E327: D27 - Department of Finance | F327: A0005 - SALARIES AND WAGES - ON PAYROLL | G327: T1576 - CHIEF VOUCHER EXPEDITER | H327: 390A73E9014727 | I327: 390A73E9014727 - ALAM, SYED S | J327: REGULAR SALARY | K327: 2023 | L327: 19 | M327: D27 | N327: F0100 | O327: A0005 | P327: T1576 | Q327: 390A73E9014727202319750868841004729
A328: $324.98 | B328: CORPORATE FUND | C328: F0100 - CORPORATE FUND | D328: Public Safety | E328: D59 - Chicago Fire Department | F328: A0020 - OVERTIME | G328: T8750 - PARAMEDIC | H328: 2884670000000 | I328: 02884666160592 - BADZIOCH, KRISTEN N | J328: OT FLSA | K328: 2023 | L328: 11 | M328: D59 | N328: F0100 | O328: A0020 | P328: T8750 | Q328: 2.88467e+33
A329: $3,347.5 | B329: CORPORATE FUND | C329: F0100 - CORPORATE FUND | D329: Public Safety | E329: D57 - Chicago Police Department | F329: A0005 - SALARIES AND WAGES - ON PAYROLL | G329: T1126 - SENIOR PERFORMANCE ANALYST | H329: 57D7B053682025 | I329: 57D7B053682025 - WILSON, LACHANYA | J329: REGULAR SALARY | K329: 2023 | L329: 23 | M329: D57 | N329: F0100 | O329: A0005 | P329: T1126 | Q329: 57D7B053682025202323933418015166748
A330: $423.93 | B330: CORPORATE FUND | C330: F0100 - CORPORATE FUND | D330: Public Safety | E330: D57 - Chicago Police Department | F330: A0020 - OVERTIME | G330: T9161 - POLICE OFFICER | H330: 7EE2E42458F6AF | I330: 7EE2E42458F6AF - VAZQUEZ, DAVE | J330: OT 1_0 | K330: 2023 | L330: 3 | M330: D57 | N330: F0100 | O330: A0020 | P330: T9161 | Q330: 7EE2E42458F6AF2023388295394157998
A331: $1,762.56 | B331: ENTERPRISE FUNDS | C331: F0200 - WATER FUND | D331: Infrastructure Services | E331: D88 - Department of Water Management | F331: A0005 - SALARIES AND WAGES - ON PAYROLL | G331: T9410 - LABORER - APPRENTICE | H331: 75916C55A99653 | I331: 75916C55A99653 - SANTIAGO, DANGELO L | J331: REGULAR TIME | K331: 2023 | L331: 3 | M331: D88 | N331: F0200 | O331: A0005 | P331: T9410 | Q331: 75916C55A9965320233748884639783407
A332: $58.08 | B332: CORPORATE FUND | C332: F0100 - CORPORATE FUND | D332: Public Safety | E332: D59 - Chicago Fire Department | F332: A0061 - DRIVER'S DIFFERENTIAL | G332: T8801 - FIREFIGHTER-EMT | H332: F14D26AE7C5E42 | I332: F14D26AE7C5E42 - FINN, PATRICK T | J332: DRIVER DIFF 1_0 | K332: 2023 | L332: 2 | M332: D59 | N332: F0100 | O332: A0061 | P332: T8801 | Q332: F14D26AE7C5E4220232176239808531430
A333: $155.97 | B333: ENTERPRISE FUNDS | C333: F0740 - CHICAGO O'HARE AIRPORT FUND | D333: Public Safety | E333: D59 - Chicago Fire Department | F333: A0020 - OVERTIME | G333: T8801 - FIREFIGHTER-EMT | H333: A8D04F45DDDFC7 | I333: A8D04F45DDDFC7 - GEMBALA, ROBERT M | J333: OT 1_5 | K333: 2023 | L333: 3 | M333: D59 | N333: F0740 | O333: A0020 | P333: T8801 | Q333: A8D04F45DDDFC72023322694413488957
A334: $-375.83 | B334: CORPORATE FUND | C334: F0100 - CORPORATE FUND | D334: City Development | E334: D54 - Department of Planning and Development | F334: A0005 - SALARIES AND WAGES - ON PAYROLL | G334: T1912 - PROJECT COORD | H334: 23815B41C0825F | I334: 23815B41C0825F - MORENO, BRIAN K | J334: DOCK | K334: 2023 | L334: 1 | M334: D54 | N334: F0100 | O334: A0005 | P334: T1912 | Q334: 23815B41C0825F20231686512917279803
A335: $4,659 | B335: CORPORATE FUND | C335: F0100 - CORPORATE FUND | D335: City Development | E335: D54 - Department of Planning and Development | F335: A0005 - SALARIES AND WAGES - ON PAYROLL | G335: T0111 - LEAD ACCOUNTANT | H335: E9F7473D7C0761 | I335: E9F7473D7C0761 - MOTA, ROSENDO | J335: REGULAR SALARY | K335: 2023 | L335: 1 | M335: D54 | N335: F0100 | O335: A0005 | P335: T0111 | Q335: E9F7473D7C076120231215755432937336
A336: $4,534 | B336: CORPORATE FUND | C336: F0100 - CORPORATE FUND | D336: City Development | E336: D54 - Department of Planning and Development | F336: A0005 - SALARIES AND WAGES - ON PAYROLL | G336: T0313 - ASST COMMISSIONER | H336: 816FFCA85FAFED | I336: 816FFCA85FAFED - ROSCHEN, MARK E | J336: REGULAR SALARY | K336: 2023 | L336: 1 | M336: D54 | N336: F0100 | O336: A0005 | P336: T0313 | Q336: 816FFCA85FAFED20231800683046880156
A337: $2,657.5 | B337: CORPORATE FUND | C337: F0100 - CORPORATE FUND | D337: City Development | E337: D54 - Department of Planning and Development | F337: A0005 - SALARIES AND WAGES - ON PAYROLL | G337: T1310 - ADMINISTRATIVE SERVICES OFFICER II EXCLD | H337: D55E0AE91386C5 | I337: D55E0AE91386C5 - ALNASER, ANNA Y | J337: REGULAR SALARY | K337: 2023 | L337: 1 | M337: D54 | N337: F0100 | O337: A0005 | P337: T1310 | Q337: D55E0AE91386C520231839225258796796
A338: $4,672 | B338: CORPORATE FUND | C338: F0100 - CORPORATE FUND | D338: City Development | E338: D54 - Department of Planning and Development | F338: A0005 - SALARIES AND WAGES - ON PAYROLL | G338: T1441 - COORDINATING PLANNER | H338: DF76509694D2CF | I338: DF76509694D2CF - GLASS, ERIK L | J338: REGULAR SALARY | K338: 2023 | L338: 1 | M338: D54 | N338: F0100 | O338: A0005 | P338: T1441 | Q338: DF76509694D2CF20231475105184735698
A339: $4,536 | B339: CORPORATE FUND | C339: F0100 - CORPORATE FUND | D339: City Development | E339: D54 - Department of Planning and Development | F339: A0005 - SALARIES AND WAGES - ON PAYROLL | G339: T1985 - COORD OF ECON DEV II - PLNG & DEV | H339: 197E06974C23C4 | I339: 197E06974C23C4 - ROBACK, BRADLEY G | J339: REGULAR SALARY | K339: 2023 | L339: 1 | M339: D54 | N339: F0100 | O339: A0005 | P339: T1985 | Q339: 197E06974C23C42023118396422507956
A340: $5,317 | B340: CORPORATE FUND | C340: F0100 - CORPORATE FUND | D340: City Development | E340: D54 - Department of Planning and Development | F340: A0005 - SALARIES AND WAGES - ON PAYROLL | G340: T9679 - DEPUTY COMMISSIONER | H340: FDA2B40E79CE73 | I340: FDA2B40E79CE73 - STRAZZABOSCO, PETER L | J340: REGULAR SALARY | K340: 2023 | L340: 1 | M340: D54 | N340: F0100 | O340: A0005 | P340: T9679 | Q340: FDA2B40E79CE7320231314356054483414
... A500: $2,140.36 | B500: CORPORATE FUND | C500: F0100 - CORPORATE FUND | D500: City Development | E500: D54 - Department of Planning and Development | F500: A0005 - SALARIES AND WAGES - ON PAYROLL | G500: T1293 - SENIOR ZONING PLAN EXAMINER | H500: 52B58AD20DA2BB | I500: 52B58AD20DA2BB - TOMBARI, EDWARD A | J500: REGULAR SALARY | K500: 2023 | L500: 12 | M500: D54 | N500: F0100 | O500: A0005 | P500: T1293 | Q500: 52B58AD20DA2BB202312837598712130836

Sheet US Employee Payroll Cleaned
A1: AMOUNT | B1: FUND | C1: DEPARTMENT FUNCTION | D1: DEPARTMENT | E1: APPROPRIATION | F1: TITLE | G1: EMPLOYEE DATASET ID | H1: EMPLOYEE NAME | I1: PAYROLL PERIOD | J1: DEPARTMENT CODE | K1: FUND CODE | L1: APPROPRIATION CODE | M1: TITLE CODE | N1: RECORD ID
A2: 3556 | B2: F0100 - CORPORATE FUND | C2: City Development | D2: D54 - Department of Planning and Development | E2: A0005 - SALARIES AND WAGES - ON PAYROLL | F2: T0109 - ACCOUNTING TECHNICIAN | G2: C1081EDB5EEAE1 | H2: TACCAD, CLARIBEL | I2: 1 | J2: D54 | K2: F0100 | L2: A0005 | M2: T0109 | N2: C1081EDB5EEAE12023142455196394809
A3: 3902.5 | B3: F0100 - CORPORATE FUND | C3: City Development | D3: D54 - Department of Planning and Development | E3: A0005 - SALARIES AND WAGES - ON PAYROLL | F3: T0303 - ADMINISTRATIVE ASST III | G3: 90D4F9839B1EE3 | H3: GRAYER, SHELIA D | I3: 1 | J3: D54 | K3: F0100 | L3: A0005 | M3: T0303 | N3: 90D4F9839B1EE320231500216338519161
A4: 3160.5 | B4: F0100 - CORPORATE FUND | C4: City Development | D4: D54 - Department of Planning and Development | E4: A0005 - SALARIES AND WAGES - ON PAYROLL | F4: T1405 - CITY PLANNER V | G4: 4146A18BC5805C | H4: CORPUZ, BENJAMIN A | I4: 1 | J4: D54 | K4: F0100 | L4: A0005 | M4: T1405 | N4: 4146A18BC5805C20231371115816750534
A5: 3711.5 | B5: F0100 - CORPORATE FUND | C5: City Development | D5: D54 - Department of Planning and Development | E5: A0005 - SALARIES AND WAGES - ON PAYROLL | F5: T1405 - CITY PLANNER V | G5: 73BA524443E82D | H5: THRUN, EMILY | I5: 1 | J5: D54 | K5: F0100 | L5: A0005 | M5: T1405 | N5: 73BA524443E82D20231918844264279950
A6: 3340.5 | B6: F0100 - CORPORATE FUND | C6: City Development | D6: D54 - Department of Planning and Development | E6: A0005 - SALARIES AND WAGES - ON PAYROLL | F6: T5402 - ARCHITECT II | G6: FABEBFAD17362B | H6: BARTON, EMILY M | I6: 1 | J6: D54 | K6: F0100 | L6: A0005 | M6: T5402 | N6: FABEBFAD17362B20231891354375792176
A7: 4274 | B7: F0100 - CORPORATE FUND | C7: City Development | D7: D54 - Department of Planning and Development | E7: A0005 - SALARIES AND WAGES - ON PAYROLL | F7: T5432 - CHIEF LANDSCAPE PLAN EXAMINER | G7: 9B82270E9FBFC9 | H7: DAYE, RONALD J | I7: 1 | J7: D54 | K7: F0100 | L7: A0005 | M7: T5432 | N7: 9B82270E9FBFC920231680319481831943
A8: -194.51 | B8: F0100 - CORPORATE FUND | C8: City Development | D8: D54 - Department of Planning and Development | E8: A0005 - SALARIES AND WAGES - ON PAYROLL | F8: T0313 - ASST COMMISSIONER | G8: 0A30E99A8A025B | H8: ALBERT, DAMIAN K | I8: 2 | J8: D54 | K8: F0100 | L8: A0005 | M8: T0313 | N8: 0A30E99A8A025B20232415253293962003
A9: 5212 | B9: F0100 - CORPORATE FUND | C9: City Development | D9: D54 - Department of Planning and Development | E9: A0005 - SALARIES AND WAGES - ON PAYROLL | F9: T0118 - DIRECTOR OF FINANCE | G9: B8E59990646B62 | H9: BUDNIK, ALESSANDRA C | I9: 2 | J9: D54 | K9: F0100 | L9: A0005 | M9: T0118 | N9: B8E59990646B622023279498489467265
A10: 3902.5 | B10: F0100 - CORPORATE FUND | C10: City Development | D10: D54 - Department of Planning and Development | E10: A0005 - SALARIES AND WAGES - ON PAYROLL | F10: T0303 - ADMINISTRATIVE ASST III | G10: 90D4F9839B1EE3 | H10: GRAYER, SHELIA D | I10: 2 | J10: D54 | K10: F0100 | L10: A0005 | M10: T0303 | N10: 90D4F9839B1EE320232197657932526116
A11: 2542.5 | B11: F0100 - CORPORATE FUND | C11: City Development | D11: D54 - Department of Planning and Development | E11: A0005 - SALARIES AND WAGES - ON PAYROLL | F11: T1293 - SENIOR ZONING PLAN EXAMINER | G11: D6F0FB9FC44E17 | H11: NOLTER, ROBERT J | I11: 2 | J11: D54 | K11: F0100 | L11: A0005 | M11: T1293 | N11: D6F0FB9FC44E1720232226438981182826
A12: 3240.5 | B12: F0100 - CORPORATE FUND | C12: City Development | D12: D54 - Department of Planning and Development | E12: A0005 - SALARIES AND WAGES - ON PAYROLL | F12: T1293 - SENIOR ZONING PLAN EXAMINER | G12: 92E1F59DF1DF8D | H12: BERAN, PETER D | I12: 2 | J12: D54 | K12: F0100 | L12: A0005 | M12: T1293 | N12: 92E1F59DF1DF8D20232725595860732288
A13: 3711.5 | B13: F0100 - CORPORATE FUND | C13: City Development | D13: D54 - Department of Planning and Development | E13: A0005 - SALARIES AND WAGES - ON PAYROLL | F13: T1405 - CITY PLANNER V | G13: 73BA524443E82D | H13: THRUN, EMILY | I13: 2 | J13: D54 | K13: F0100 | L13: A0005 | M13: T1405 | N13: 73BA524443E82D20232743816382565908
... A327: 4982.5 | B327: F0100 - CORPORATE FUND | C327: Finance and Administration | D327: D27 - Department of Finance | E327: A0005 - SALARIES AND WAGES - ON PAYROLL | F327: T1576 - CHIEF VOUCHER EXPEDITER | G327: 390A73E9014727 | H327: ALAM, SYED S | I327: 19 | J327: D27 | K327: F0100 | L327: A0005 | M327: T1576 | N327: 390A73E9014727202319750868841004729
A328: 324.98 | B328: F0100 - CORPORATE FUND | C328: Public Safety | D328: D59 - Chicago Fire Department | E328: A0020 - OVERTIME | F328: T8750 - PARAMEDIC | G328: 2884670000000 | H328: BADZIOCH, KRISTEN N | I328: 11 | J328: D59 | K328: F0100 | L328: A0020 | M328: T8750 | N328: 2.88467e+33
A329: 3347.5 | B329: F0100 - CORPORATE FUND | C329: Public Safety | D329: D57 - Chicago Police Department | E329: A0005 - SALARIES AND WAGES - ON PAYROLL | F329: T1126 - SENIOR PERFORMANCE ANALYST | G329: 57D7B053682025 | H329: WILSON, LACHANYA | I329: 23 | J329: D57 | K329: F0100 | L329: A0005 | M329: T1126 | N329: 57D7B053682025202323933418015166748
A330: 423.93 | B330: F0100 - CORPORATE FUND | C330: Public Safety | D330: D57 - Chicago Police Department | E330: A0020 - OVERTIME | F330: T9161 - POLICE OFFICER | G330: 7EE2E42458F6AF | H330: VAZQUEZ, DAVE | I330: 3 | J330: D57 | K330: F0100 | L330: A0020 | M330: T9161 | N330: 7EE2E42458F6AF2023388295394157998
A331: 1762.56 | B331: F0200 - WATER FUND | C331: Infrastructure Services | D331: D88 - Department of Water Management | E331: A0005 - SALARIES AND WAGES - ON PAYROLL | F331: T9410 - LABORER - APPRENTICE | G331: 75916C55A99653 | H331: SANTIAGO, DANGELO L | I331: 3 | J331: D88 | K331: F0200 | L331: A0005 | M331: T9410 | N331: 75916C55A9965320233748884639783407
A332: 58.08 | B332: F0100 - CORPORATE FUND | C332: Public Safety | D332: D59 - Chicago Fire Department | E332: A0061 - DRIVER'S DIFFERENTIAL | F332: T8801 - FIREFIGHTER-EMT | G332: F14D26AE7C5E42 | H332: FINN, PATRICK T | I332: 2 | J332: D59 | K332: F0100 | L332: A0061 | M332: T8801 | N332: F14D26AE7C5E4220232176239808531430
A333: 155.97 | B333: F0740 - CHICAGO O'HARE AIRPORT FUND | C333: Public Safety | D333: D59 - Chicago Fire Department | E333: A0020 - OVERTIME | F333: T8801 - FIREFIGHTER-EMT | G333: A8D04F45DDDFC7 | H333: GEMBALA, ROBERT M | I333: 3 | J333: D59 | K333: F0740 | L333: A0020 | M333: T8801 | N333: A8D04F45DDDFC72023322694413488957
A334: -375.83 | B334: F0100 - CORPORATE FUND | C334: City Development | D334: D54 - Department of Planning and Development | E334: A0005 - SALARIES AND WAGES - ON PAYROLL | F334: T1912 - PROJECT COORD | G334: 23815B41C0825F | H334: MORENO, BRIAN K | I334: 1 | J334: D54 | K334: F0100 | L334: A0005 | M334: T1912 | N334: 23815B41C0825F20231686512917279803
A335: 4659 | B335: F0100 - CORPORATE FUND | C335: City Development | D335: D54 - Department of Planning and Development | E335: A0005 - SALARIES AND WAGES - ON PAYROLL | F335: T0111 - LEAD ACCOUNTANT | G335: E9F7473D7C0761 | H335: MOTA, ROSENDO | I335: 1 | J335: D54 | K335: F0100 | L335: A0005 | M335: T0111 | N335: E9F7473D7C076120231215755432937336
A336: 4534 | B336: F0100 - CORPORATE FUND | C336: City Development | D336: D54 - Department of Planning and Development | E336: A0005 - SALARIES AND WAGES - ON PAYROLL | F336: T0313 - ASST COMMISSIONER | G336: 816FFCA85FAFED | H336: ROSCHEN, MARK E | I336: 1 | J336: D54 | K336: F0100 | L336: A0005 | M336: T0313 | N336: 816FFCA85FAFED20231800683046880156
A337: 2657.5 | B337: F0100 - CORPORATE FUND | C337: City Development | D337: D54 - Department of Planning and Development | E337: A0005 - SALARIES AND WAGES - ON PAYROLL | F337: T1310 - ADMINISTRATIVE SERVICES OFFICER II EXCLD | G337: D55E0AE91386C5 | H337: ALNASER, ANNA Y | I337: 1 | J337: D54 | K337: F0100 | L337: A0005 | M337: T1310 | N337: D55E0AE91386C520231839225258796796
A338: 4672 | B338: F0100 - CORPORATE FUND | C338: City Development | D338: D54 - Department of Planning and Development | E338: A0005 - SALARIES AND WAGES - ON PAYROLL | F338: T1441 - COORDINATING PLANNER | G338: DF76509694D2CF | H338: GLASS, ERIK L | I338: 1 | J338: D54 | K338: F0100 | L338: A0005 | M338: T1441 | N338: DF76509694D2CF20231475105184735698
A339: 4536 | B339: F0100 - CORPORATE FUND | C339: City Development | D339: D54 - Department of Planning and Development | E339: A0005 - SALARIES AND WAGES - ON PAYROLL | F339: T1985 - COORD OF ECON DEV II - PLNG & DEV | G339: 197E06974C23C4 | H339: ROBACK, BRADLEY G | I339: 1 | J339: D54 | K339: F0100 | L339: A0005 | M339: T1985 | N339: 197E06974C23C42023118396422507956
A340: 5317 | B340: F0100 - CORPORATE FUND | C340: City Development | D340: D54 - Department of Planning and Development | E340: A0005 - SALARIES AND WAGES - ON PAYROLL | F340: T9679 - DEPUTY COMMISSIONER | G340: FDA2B40E79CE73 | H340: STRAZZABOSCO, PETER L | I340: 1 | J340: D54 | K340: F0100 | L340: A0005 | M340: T9679 | N340: FDA2B40E79CE7320231314356054483414
... A500: 2140.36 | B500: F0100 - CORPORATE FUND | C500: City Development | D500: D54 - Department of Planning and Development | E500: A0005 - SALARIES AND WAGES - ON PAYROLL | F500: T1293 - SENIOR ZONING PLAN EXAMINER | G500: 52B58AD20DA2BB | H500: TOMBARI, EDWARD A | I500: 12 | J500: D54 | K500: F0100 | L500: A0005 | M500: T1293 | N500: 52B58AD20DA2BB202312837598712130836

Sheet Lookup Sheet
A1: Employee Data Set ID | B1: Employee Name (vlookup) | C1: Payroll Amount (Index/match) | D1: Employee Name (Xlookup) | G1: Employee Name | H1: TACCAD, CLARIBEL | I1: GRAYER, SHELIA D | J1: CORPUZ, BENJAMIN A | K1: THRUN, EMILY | L1: BARTON, EMILY M | M1: DAYE, RONALD J | N1: ALBERT, DAMIAN K | O1: BUDNIK, ALESSANDRA C | P1: GRAYER, SHELIA D | Q1: NOLTER, ROBERT J | R1: BERAN, PETER D | S1: THRUN, EMILY | T1: WEBER, MICHAEL P | U1: NELSON, GABRIELLA M | V1: HERTZ, DANIEL K | W1: THOMPSON, TAYLOR J | X1: ROBACK, BRADLEY G | Y1: OCIEPKA, LESZEK | Z1: WEBER, MICHAEL P
A2: C1081EDB5EEAE1 | B2: =VLOOKUP(A2,'US Employee Payroll Cleaned'!G:N,2,FALSE) -> TACCAD, CLARIBEL | C2: =INDEX('US Employee Payroll Cleaned'!A:A,MATCH('Lookup Sheet'!A2,'US Employee Payroll Cleaned'!G:G,0)) -> 3556 | D2: =_xlfn.XLOOKUP(A2,'US Employee Payroll Cleaned'!G:G,'US Employee Payroll Cleaned'!H:H,"Not found") -> TACCAD, CLARIBEL | G2: Amount | H2: 3556 | I2: 3902.5 | J2: 3160.5 | K2: 3711.5 | L2: 3340.5 | M2: 4274 | N2: -194.51 | O2: 5212 | P2: 3902.5 | Q2: 2542.5 | R2: 3240.5 | S2: 3711.5 | T2: 4534 | U2: 3607.5 | V2: 4766 | W2: 2708 | X2: 4536 | Y2: 4271.5 | Z2: 4534
A3: 90D4F9839B1EE3 | B3: =VLOOKUP(A3,'US Employee Payroll Cleaned'!G:N,2,FALSE) -> GRAYER, SHELIA D | C3: =INDEX('US Employee Payroll Cleaned'!A:A,MATCH('Lookup Sheet'!A3,'US Employee Payroll Cleaned'!G:G,0)) -> 3902.5 | D3: =_xlfn.XLOOKUP(A3,'US Employee Payroll Cleaned'!G:G,'US Employee Payroll Cleaned'!H:H,"Not found") -> GRAYER, SHELIA D | G3: Employee ID | H3: C1081EDB5EEAE1 | I3: 90D4F9839B1EE3 | J3: 4146A18BC5805C | K3: 73BA524443E82D | L3: FABEBFAD17362B | M3: 9B82270E9FBFC9 | N3: 0A30E99A8A025B | O3: B8E59990646B62 | P3: 90D4F9839B1EE3 | Q3: D6F0FB9FC44E17 | R3: 92E1F59DF1DF8D | S3: 73BA524443E82D | T3: B1DCE5C3C3A044 | U3: 1AFFC8FE80ACB6 | V3: C28E727C8EB8AF | W3: C57C9A2F1A1F8D | X3: 197E06974C23C4 | Y3: 6AE3E9CF0CE168 | Z3: B1DCE5C3C3A044
A4: 4146A18BC5805C | B4: =VLOOKUP(A4,'US Employee Payroll Cleaned'!G:N,2,FALSE) -> CORPUZ, BENJAMIN A | C4: =INDEX('US Employee Payroll Cleaned'!A:A,MATCH('Lookup Sheet'!A4,'US Employee Payroll Cleaned'!G:G,0)) -> 3160.5 | D4: =_xlfn.XLOOKUP(A4,'US Employee Payroll Cleaned'!G:G,'US Employee Payroll Cleaned'!H:H,"Not found") -> CORPUZ, BENJAMIN A | G4: Employee ID (Hlookup) | H4: =HLOOKUP(H1,H1:Z3,3,FALSE) -> C1081EDB5EEAE1 | I4: =HLOOKUP(I1,I1:AA3,3,FALSE) -> 90D4F9839B1EE3 | J4: =HLOOKUP(J1,J1:AB3,3,FALSE) -> 4146A18BC5805C | K4: =HLOOKUP(K1,K1:AC3,3,FALSE) -> 73BA524443E82D | L4: =HLOOKUP(L1,L1:AD3,3,FALSE) -> FABEBFAD17362B | M4: =HLOOKUP(M1,M1:AE3,3,FALSE) -> 9B82270E9FBFC9 | N4: =HLOOKUP(N1,N1:AF3,3,FALSE) -> 0A30E99A8A025B | O4: =HLOOKUP(O1,O1:AG3,3,FALSE) -> B8E59990646B62 | ... Z4: =HLOOKUP(Z1,Z1:AR3,3,FALSE) -> B1DCE5C3C3A044
A5: 73BA524443E82D | B5: =VLOOKUP(A5,'US Employee Payroll Cleaned'!G:N,2,FALSE) -> THRUN, EMILY | C5: =INDEX('US Employee Payroll Cleaned'!A:A,MATCH('Lookup Sheet'!A5,'US Employee Payroll Cleaned'!G:G,0)) -> 3711.5 | D5: =_xlfn.XLOOKUP(A5,'US Employee Payroll Cleaned'!G:G,'US Employee Payroll Cleaned'!H:H,"Not found") -> THRUN, EMILY
A6: FABEBFAD17362B | B6: =VLOOKUP(A6,'US Employee Payroll Cleaned'!G:N,2,FALSE) -> BARTON, EMILY M | C6: =INDEX('US Employee Payroll Cleaned'!A:A,MATCH('Lookup Sheet'!A6,'US Employee Payroll Cleaned'!G:G,0)) -> 3340.5 | D6: =_xlfn.XLOOKUP(A6,'US Employee Payroll Cleaned'!G:G,'US Employee Payroll Cleaned'!H:H,"Not found") -> BARTON, EMILY M
A7: 9B82270E9FBFC9 | B7: =VLOOKUP(A7,'US Employee Payroll Cleaned'!G:N,2,FALSE) -> DAYE, RONALD J | C7: =INDEX('US Employee Payroll Cleaned'!A:A,MATCH('Lookup Sheet'!A7,'US Employee Payroll Cleaned'!G:G,0)) -> 4274 | D7: =_xlfn.XLOOKUP(A7,'US Employee Payroll Cleaned'!G:G,'US Employee Payroll Cleaned'!H:H,"Not found") -> DAYE, RONALD J
A8: 0A30E99A8A025B | B8: =VLOOKUP(A8,'US Employee Payroll Cleaned'!G:N,2,FALSE) -> ALBERT, DAMIAN K | C8: =INDEX('US Employee Payroll Cleaned'!A:A,MATCH('Lookup Sheet'!A8,'US Employee Payroll Cleaned'!G:G,0)) -> -194.51 | D8: =_xlfn.XLOOKUP(A8,'US Employee Payroll Cleaned'!G:G,'US Employee Payroll Cleaned'!H:H,"Not found") -> ALBERT, DAMIAN K
A9: B8E59990646B62 | B9: =VLOOKUP(A9,'US Employee Payroll Cleaned'!G:N,2,FALSE) -> BUDNIK, ALESSANDRA C | C9: =INDEX('US Employee Payroll Cleaned'!A:A,MATCH('Lookup Sheet'!A9,'US Employee Payroll Cleaned'!G:G,0)) -> 5212 | D9: =_xlfn.XLOOKUP(A9,'US Employee Payroll Cleaned'!G:G,'US Employee Payroll Cleaned'!H:H,"Not found") -> BUDNIK, ALESSANDRA C
A10: 90D4F9839B1EE3 | B10: =VLOOKUP(A10,'US Employee Payroll Cleaned'!G:N,2,FALSE) -> GRAYER, SHELIA D | C10: =INDEX('US Employee Payroll Cleaned'!A:A,MATCH('Lookup Sheet'!A10,'US Employee Payroll Cleaned'!G:G,0)) -> 3902.5 | D10: =_xlfn.XLOOKUP(A10,'US Employee Payroll Cleaned'!G:G,'US Employee Payroll Cleaned'!H:H,"Not found") -> GRAYER, SHELIA D
A11: D6F0FB9FC44E17 | B11: =VLOOKUP(A11,'US Employee Payroll Cleaned'!G:N,2,FALSE) -> NOLTER, ROBERT J | C11: =INDEX('US Employee Payroll Cleaned'!A:A,MATCH('Lookup Sheet'!A11,'US Employee Payroll Cleaned'!G:G,0)) -> 2542.5 | D11: =_xlfn.XLOOKUP(A11,'US Employee Payroll Cleaned'!G:G,'US Employee Payroll Cleaned'!H:H,"Not found") -> NOLTER, ROBERT J
A12: 92E1F59DF1DF8D | B12: =VLOOKUP(A12,'US Employee Payroll Cleaned'!G:N,2,FALSE) -> BERAN, PETER D | C12: =INDEX('US Employee Payroll Cleaned'!A:A,MATCH('Lookup Sheet'!A12,'US Employee Payroll Cleaned'!G:G,0)) -> 3240.5 | D12: =_xlfn.XLOOKUP(A12,'US Employee Payroll Cleaned'!G:G,'US Employee Payroll Cleaned'!H:H,"Not found") -> BERAN, PETER D
A13: 73BA524443E82D | B13: =VLOOKUP(A13,'US Employee Payroll Cleaned'!G:N,2,FALSE) -> THRUN, EMILY | C13: =INDEX('US Employee Payroll Cleaned'!A:A,MATCH('Lookup Sheet'!A13,'US Employee Payroll Cleaned'!G:G,0)) -> 3711.5 | D13: =_xlfn.XLOOKUP(A13,'US Employee Payroll Cleaned'!G:G,'US Employee Payroll Cleaned'!H:H,"Not found") -> THRUN, EMILY
A14: B1DCE5C3C3A044 | B14: =VLOOKUP(A14,'US Employee Payroll Cleaned'!G:N,2,FALSE) -> WEBER, MICHAEL P | C14: =INDEX('US Employee Payroll Cleaned'!A:A,MATCH('Lookup Sheet'!A14,'US Employee Payroll Cleaned'!G:G,0)) -> 4534 | D14: =_xlfn.XLOOKUP(A14,'US Employee Payroll Cleaned'!G:G,'US Employee Payroll Cleaned'!H:H,"Not found") -> WEBER, MICHAEL P
A15: 1AFFC8FE80ACB6 | B15: =VLOOKUP(A15,'US Employee Payroll Cleaned'!G:N,2,FALSE) -> NELSON, GABRIELLA M | C15: =INDEX('US Employee Payroll Cleaned'!A:A,MATCH('Lookup Sheet'!A15,'US Employee Payroll Cleaned'!G:G,0)) -> 3607.5 | D15: =_xlfn.XLOOKUP(A15,'US Employee Payroll Cleaned'!G:G,'US Employee Payroll Cleaned'!H:H,"Not found") -> NELSON, GABRIELLA M
A16: C28E727C8EB8AF | B16: =VLOOKUP(A16,'US Employee Payroll Cleaned'!G:N,2,FALSE) -> HERTZ, DANIEL K | C16: =INDEX('US Employee Payroll Cleaned'!A:A,MATCH('Lookup Sheet'!A16,'US Employee Payroll Cleaned'!G:G,0)) -> 4766 | D16: =_xlfn.XLOOKUP(A16,'US Employee Payroll Cleaned'!G:G,'US Employee Payroll Cleaned'!H:H,"Not found") -> HERTZ, DANIEL K
... A327: 390A73E9014727 | B327: =VLOOKUP(A327,'US Employee Payroll Cleaned'!G:N,2,FALSE) -> ALAM, SYED S | C327: =INDEX('US Employee Payroll Cleaned'!A:A,MATCH('Lookup Sheet'!A327,'US Employee Payroll Cleaned'!G:G,0)) -> 4982.5 | D327: =_xlfn.XLOOKUP(A327,'US Employee Payroll Cleaned'!G:G,'US Employee Payroll Cleaned'!H:H,"Not found") -> ALAM, SYED S
A328: 2884670000000 | B328: =VLOOKUP(A328,'US Employee Payroll Cleaned'!G:N,2,FALSE) -> BADZIOCH, KRISTEN N | C328: =INDEX('US Employee Payroll Cleaned'!A:A,MATCH('Lookup Sheet'!A328,'US Employee Payroll Cleaned'!G:G,0)) -> 324.98 | D328: =_xlfn.XLOOKUP(A328,'US Employee Payroll Cleaned'!G:G,'US Employee Payroll Cleaned'!H:H,"Not found") -> BADZIOCH, KRISTEN N
A329: 57D7B053682025 | B329: =VLOOKUP(A329,'US Employee Payroll Cleaned'!G:N,2,FALSE) -> WILSON, LACHANYA | C329: =INDEX('US Employee Payroll Cleaned'!A:A,MATCH('Lookup Sheet'!A329,'US Employee Payroll Cleaned'!G:G,0)) -> 3347.5 | D329: =_xlfn.XLOOKUP(A329,'US Employee Payroll Cleaned'!G:G,'US Employee Payroll Cleaned'!H:H,"Not found") -> WILSON, LACHANYA
A330: 7EE2E42458F6AF | B330: =VLOOKUP(A330,'US Employee Payroll Cleaned'!G:N,2,FALSE) -> VAZQUEZ, DAVE | C330: =INDEX('US Employee Payroll Cleaned'!A:A,MATCH('Lookup Sheet'!A330,'US Employee Payroll Cleaned'!G:G,0)) -> 423.93 | D330: =_xlfn.XLOOKUP(A330,'US Employee Payroll Cleaned'!G:G,'US Employee Payroll Cleaned'!H:H,"Not found") -> VAZQUEZ, DAVE
A331: 75916C55A99653 | B331: =VLOOKUP(A331,'US Employee Payroll Cleaned'!G:N,2,FALSE) -> SANTIAGO, DANGELO L | C331: =INDEX('US Employee Payroll Cleaned'!A:A,MATCH('Lookup Sheet'!A331,'US Employee Payroll Cleaned'!G:G,0)) -> 1762.56 | D331: =_xlfn.XLOOKUP(A331,'US Employee Payroll Cleaned'!G:G,'US Employee Payroll Cleaned'!H:H,"Not found") -> SANTIAGO, DANGELO L
A332: F14D26AE7C5E42 | B332: =VLOOKUP(A332,'US Employee Payroll Cleaned'!G:N,2,FALSE) -> FINN, PATRICK T | C332: =INDEX('US Employee Payroll Cleaned'!A:A,MATCH('Lookup Sheet'!A332,'US Employee Payroll Cleaned'!G:G,0)) -> 58.08 | D332: =_xlfn.XLOOKUP(A332,'US Employee Payroll Cleaned'!G:G,'US Employee Payroll Cleaned'!H:H,"Not found") -> FINN, PATRICK T
A333: A8D04F45DDDFC7 | B333: =VLOOKUP(A333,'US Employee Payroll Cleaned'!G:N,2,FALSE) -> GEMBALA, ROBERT M | C333: =INDEX('US Employee Payroll Cleaned'!A:A,MATCH('Lookup Sheet'!A333,'US Employee Payroll Cleaned'!G:G,0)) -> 155.97 | D333: =_xlfn.XLOOKUP(A333,'US Employee Payroll Cleaned'!G:G,'US Employee Payroll Cleaned'!H:H,"Not found") -> GEMBALA, ROBERT M
A334: 23815B41C0825F | B334: =VLOOKUP(A334,'US Employee Payroll Cleaned'!G:N,2,FALSE) -> MORENO, BRIAN K | C334: =INDEX('US Employee Payroll Cleaned'!A:A,MATCH('Lookup Sheet'!A334,'US Employee Payroll Cleaned'!G:G,0)) -> -1378.03 | D334: =_xlfn.XLOOKUP(A334,'US Employee Payroll Cleaned'!G:G,'US Employee Payroll Cleaned'!H:H,"Not found") -> MORENO, BRIAN K
A335: E9F7473D7C0761 | B335: =VLOOKUP(A335,'US Employee Payroll Cleaned'!G:N,2,FALSE) -> MOTA, ROSENDO | C335: =INDEX('US Employee Payroll Cleaned'!A:A,MATCH('Lookup Sheet'!A335,'US Employee Payroll Cleaned'!G:G,0)) -> 4659 | D335: =_xlfn.XLOOKUP(A335,'US Employee Payroll Cleaned'!G:G,'US Employee Payroll Cleaned'!H:H,"Not found") -> MOTA, ROSENDO
A336: 816FFCA85FAFED | B336: =VLOOKUP(A336,'US Employee Payroll Cleaned'!G:N,2,FALSE) -> ROSCHEN, MARK E | C336: =INDEX('US Employee Payroll Cleaned'!A:A,MATCH('Lookup Sheet'!A336,'US Employee Payroll Cleaned'!G:G,0)) -> 4534 | D336: =_xlfn.XLOOKUP(A336,'US Employee Payroll Cleaned'!G:G,'US Employee Payroll Cleaned'!H:H,"Not found") -> ROSCHEN, MARK E
A337: D55E0AE91386C5 | B337: =VLOOKUP(A337,'US Employee Payroll Cleaned'!G:N,2,FALSE) -> ALNASER, ANNA Y | C337: =INDEX('US Employee Payroll Cleaned'!A:A,MATCH('Lookup Sheet'!A337,'US Employee Payroll Cleaned'!G:G,0)) -> 2783.5 | D337: =_xlfn.XLOOKUP(A337,'US Employee Payroll Cleaned'!G:G,'US Employee Payroll Cleaned'!H:H,"Not found") -> ALNASER, ANNA Y
A338: DF76509694D2CF | B338: =VLOOKUP(A338,'US Employee Payroll Cleaned'!G:N,2,FALSE) -> GLASS, ERIK L | C338: =INDEX('US Employee Payroll Cleaned'!A:A,MATCH('Lookup Sheet'!A338,'US Employee Payroll Cleaned'!G:G,0)) -> 4672 | D338: =_xlfn.XLOOKUP(A338,'US Employee Payroll Cleaned'!G:G,'US Employee Payroll Cleaned'!H:H,"Not found") -> GLASS, ERIK L
A339: 197E06974C23C4 | B339: =VLOOKUP(A339,'US Employee Payroll Cleaned'!G:N,2,FALSE) -> ROBACK, BRADLEY G | C339: =INDEX('US Employee Payroll Cleaned'!A:A,MATCH('Lookup Sheet'!A339,'US Employee Payroll Cleaned'!G:G,0)) -> 4536 | D339: =_xlfn.XLOOKUP(A339,'US Employee Payroll Cleaned'!G:G,'US Employee Payroll Cleaned'!H:H,"Not found") -> ROBACK, BRADLEY G
A340: FDA2B40E79CE73 | B340: =VLOOKUP(A340,'US Employee Payroll Cleaned'!G:N,2,FALSE) -> STRAZZABOSCO, PETER L | C340: =INDEX('US Employee Payroll Cleaned'!A:A,MATCH('Lookup Sheet'!A340,'US Employee Payroll Cleaned'!G:G,0)) -> 5317 | D340: =_xlfn.XLOOKUP(A340,'US Employee Payroll Cleaned'!G:G,'US Employee Payroll Cleaned'!H:H,"Not found") -> STRAZZABOSCO, PETER L
... A500: 52B58AD20DA2BB | B500: =VLOOKUP(A500,'US Employee Payroll Cleaned'!G:N,2,FALSE) -> TOMBARI, EDWARD A | C500: =INDEX('US Employee Payroll Cleaned'!A:A,MATCH('Lookup Sheet'!A500,'US Employee Payroll Cleaned'!G:G,0)) -> 2140.36 | D500: =_xlfn.XLOOKUP(A500,'US Employee Payroll Cleaned'!G:G,'US Employee Payroll Cleaned'!H:H,"Not found") -> TOMBARI, EDWARD A

Sheet Department Payroll Analysis
A3: Row Labels | B3: Sum of AMOUNT
A4: D21 - Department of Housing | B4: 389719.67
A5: D27 - Department of Finance | B5: 7571.5
A6: D38 - Department of Fleet and Facility Management | B6: 3316.59
A7: D50 - Department of Family and Support Services | B7: 180.08
A8: D54 - Department of Planning and Development | B8: 1187060.2
A9: D57 - Chicago Police Department | B9: 101874.78
A10: D58 - Office of Emergency Management and Communications | B10: 5416.08
A11: D59 - Chicago Fire Department | B11: 20075.58
A12: D67 - Department of Buildings | B12: 769.44
A13: D73 - Chicago Animal Care and Control | B13: 1934
A14: D81 - Department of Streets and Sanitation | B14: 6530.21
A15: D84 - Chicago Department of Transportation | B15: 10964.9
... A19: Grand Total | B19: 1744230

Sheet Payroll By Job Title
A1: Payroll By Job Title | D1: Payroll By Payperiod
A3: Row Labels | B3: Sum of AMOUNT | D3: Row Labels | E3: Sum of AMOUNT
A4: T0109 - ACCOUNTING TECHNICIAN | B4: 20989.5 | D4: 1 | E4: 164702.78
A5: T0110 - ACCOUNTANT | B5: 180.08 | D5: 2 | E5: 135711.87
A6: T0111 - LEAD ACCOUNTANT | B6: 9318 | D6: 3 | E6: 137388.97
A7: T0118 - DIRECTOR OF FINANCE | B7: 15825.5 | D7: 4 | E7: 161100.6
A8: T0303 - ADMINISTRATIVE ASST III | B8: 21831.98 | D8: 5 | E8: 139924.49
A9: T0304 - ASST TO THE COMMISSIONER | B9: 19906 | D9: 6 | E9: 171131.23
A10: T0308 - STAFF ASST | B10: 28928 | D10: 7 | E10: 153431.6
A11: T0310 - PROJECT MANAGER | B11: 150476 | D11: 8 | E11: 141417.22
A12: T0313 - ASST COMMISSIONER | B12: 116162.13 | D12: 9 | E12: 170354.97
A13: T0361 - DIR OF PERSONNEL POLICIES AND UTILIZATION | B13: 5212 | D13: 10 | E13: 125120.69
A14: T0366 - STAFF ASSISTANT - EXCLUDED | B14: 8654.11 | D14: 11 | E14: 119692.36
A15: T0381 - DIR OF ADMINISTRATION II | B15: 25002.5 | D15: 12 | E15: 32543.74
... A26: T1290 - MANAGER - ZONING BD OF APPEALS | B26: 13822.5 | D26: 24 | E26: 4779.04
A27: T1291 - ZONING INVESTIGATOR | B27: 32739 | D27: Grand Total | E27: 1744230
A28: T1293 - SENIOR ZONING PLAN EXAMINER | B28: 128566.86
A29: T1299 - CHIEF ZONING PLAN EXAMINER | B29: 10424
A30: T1310 - ADMINISTRATIVE SERVICES OFFICER II EXCLD | B30: 10882
A31: T1315 - HUMAN RESOURCES BUSINESS PARTNER-EXCLD | B31: 4330
A32: T1402 - CITY PLANNER II | B32: 3754.5
A33: T1405 - CITY PLANNER V | B33: 133222.2
A34: T1407 - URBAN DESIGNER | B34: 9660.5
A35: T1408 - SUPERVISING PLANNER | B35: 25442
A36: T1430 - POLICY ANALYST | B36: 29535
A37: T1437 - FINANCIAL PLANNING ANALYST - EXCLD | B37: 37472
A38: T1441 - COORDINATING PLANNER | B38: 58288
A39: T1576 - CHIEF VOUCHER EXPEDITER | B39: 4982.5
... A89: Grand Total | B89: 1744230
